odoo/addons/portal_partner_data_no_edit/README.rst
odoo/addons/portal_partner_data_no_edit/__init__.py
odoo/addons/portal_partner_data_no_edit/__manifest__.py
odoo/addons/portal_partner_data_no_edit/controllers/__init__.py
odoo/addons/portal_partner_data_no_edit/controllers/portal.py
odoo/addons/portal_partner_data_no_edit/i18n/es.po
odoo/addons/portal_partner_data_no_edit/i18n/portal_partner_data_no_edit.pot
odoo/addons/portal_partner_data_no_edit/models/__init__.py
odoo/addons/portal_partner_data_no_edit/models/ir_ui_view.py
odoo/addons/portal_partner_data_no_edit/models/res_partner.py
odoo/addons/portal_partner_data_no_edit/readme/CONFIGURE.rst
odoo/addons/portal_partner_data_no_edit/readme/CONTRIBUTORS.rst
odoo/addons/portal_partner_data_no_edit/readme/DESCRIPTION.rst
odoo/addons/portal_partner_data_no_edit/readme/ROADMAP.rst
odoo/addons/portal_partner_data_no_edit/readme/USAGE.rst
odoo/addons/portal_partner_data_no_edit/static/description/icon.png
odoo/addons/portal_partner_data_no_edit/static/description/index.html
odoo/addons/portal_partner_data_no_edit/static/src/js/portal_partner_data_no_edit_tour.js
odoo/addons/portal_partner_data_no_edit/tests/__init__.py
odoo/addons/portal_partner_data_no_edit/tests/test_portal_partner_data_no_edit.py
odoo/addons/portal_partner_data_no_edit/views/portal_template.xml
odoo/addons/portal_partner_data_no_edit/views/res_partner_views.xml
odoo_addon_portal_partner_data_no_edit-15.0.1.0.0.5.dist-info/METADATA
odoo_addon_portal_partner_data_no_edit-15.0.1.0.0.5.dist-info/WHEEL
odoo_addon_portal_partner_data_no_edit-15.0.1.0.0.5.dist-info/top_level.txt
odoo_addon_portal_partner_data_no_edit-15.0.1.0.0.5.dist-info/RECORD
